TikTokLive/__init__.py
TikTokLive/utilities.py
TikTokLive/client/__init__.py
TikTokLive/client/base.py
TikTokLive/client/client.py
TikTokLive/client/config.py
TikTokLive/client/httpx.py
TikTokLive/client/wsclient.py
TikTokLive/proto/__init__.py
TikTokLive/proto/tiktok_schema_pb2.py
TikTokLive/proto/utilities.py
TikTokLive/types/__init__.py
TikTokLive/types/errors.py
TikTokLive/types/events.py
TikTokLive/types/objects.py
TikTokLive/types/utilities.py
TikTokLiveCustom-0.4.dist-info/LICENSE
TikTokLiveCustom-0.4.dist-info/METADATA
TikTokLiveCustom-0.4.dist-info/WHEEL
TikTokLiveCustom-0.4.dist-info/top_level.txt
TikTokLiveCustom-0.4.dist-info/RECORD
